{"type":"FeatureCollection","features":[{"type":"Feature","properties":{"marker-color":"#7e7e7e","marker-size":"medium","marker-symbol":"","name":"My Home"},"geometry":{"type":"Point","coordinates":[-87.78991341590881,41.99652986892937]}},{"type":"Feature","properties":{},"geometry":{"type":"Point","coordinates":[-87.78989732265472,41.99734116878555]}},{"type":"Feature","properties":{},"geometry":{"type":"Point","coordinates":[-87.77494668960571,41.99745478980706]}},{"type":"Feature","properties":{},"geometry":{"type":"Point","coordinates":[-87.77056932449341,41.99716774683531]}},{"type":"Feature","properties":{},"geometry":{"type":"Point","coordinates":[-87.76679277420044,41.99732721531279]}},{"type":"Feature","properties":{},"geometry":{"type":"Point","coordinates":[-87.75200843811035,41.990549452627576]}},{"type":"Feature","properties":{},"geometry":{"type":"Point","coordinates":[-87.74926185607909,41.98991150838941]}},{"type":"Feature","properties":{},"geometry":{"type":"Point","coordinates":[-87.72868394851685,41.99015073822795]}},{"type":"Feature","properties":{},"geometry":{"type":"Point","coordinates":[-87.72844791412354,41.98281394753941]}},{"type":"Feature","properties":{},"geometry":{"type":"Point","coordinates":[-87.72095918655396,41.98290965025154]}},{"type":"Feature","properties":{},"geometry":{"type":"Point","coordinates":[-87.7208948135376,41.97940045674709]}},{"type":"Feature","properties":{"marker-color":"#7e7e7e","marker-size":"medium","marker-symbol":"","name":"NEIU"},"geometry":{"type":"Point","coordinates":[-87.71969318389891,41.97940045674709]}}]}